fastshell/__init__.py
fastshell/app.py
fastshell/command.py
fastshell/completer.py
fastshell/exceptions.py
fastshell/formatter.py
fastshell/parser.py
fastshell/types.py
fastshell/utils.py
fastshell/validation.py
fastshell-0.1.3.dist-info/entry_points.txt
fastshell-0.1.3.dist-info/LICENSE
fastshell-0.1.3.dist-info/METADATA
fastshell-0.1.3.dist-info/WHEEL
fastshell-0.1.3.dist-info/RECORD
