Metadata-Version: 2.3
Name: fastshell
Version: 0.1.3
Summary: A FastAPI-like framework for building interactive shell applications with auto-completion and type safety
License: GPLv3
Author: originalFactor
Author-email: 2438926613@qq.com
Requires-Python: >=3.8
Classifier: Development Status :: 3 - Alpha
Classifier: Intended Audience :: Developers
Classifier: License :: OSI Approved :: GNU General Public License v3 or later (GPLv3+)
Classifier: Operating System :: OS Independent
Classifier: Programming Language :: Python :: 3
Classifier: Programming Language :: Python :: 3.8
Classifier: Programming Language :: Python :: 3.9
Classifier: Programming Language :: Python :: 3.10
Classifier: Programming Language :: Python :: 3.11
Requires-Dist: prompt-toolkit (>=3.0.0,<4.0.0)
Requires-Dist: pydantic (>=2.0.0,<3.0.0)
Requires-Dist: rich (>=13.0.0,<15.0.0)
Requires-Dist: typing-extensions (>=4.0.0,<5.0.0)
Project-URL: Homepage, https://github.com/originalfactor/fastshell
Project-URL: Issues, https://github.com/originalfactor/fastshell/issues
